{
  "service": "celery",
  "scan_timestamp": "2026-03-27T07:45:01.115098",
  "finding_count": 1,
  "findings": [
    {
      "service": "celery",
      "file": "docker/env/.env.example.app",
      "repository": "bakrianoo/mini-rag",
      "url": "https://github.com/bakrianoo/mini-rag/blob/77050419ad3dd749702fdbea71e6181e376afcd3/docker/env/.env.example.app",
      "line_number": 49,
      "line_preview": "CELERY_FLOWER_PASSWORD=\"minirag_flower_2222\"",
      "key_type": "celery_flower_password",
      "description": "Celery Flower Password",
      "severity": "high",
      "matched_pattern": "mini***********2222",
      "timestamp": "2026-03-27T07:43:51.005571"
    }
  ]
}