{
  "service": "huggingface",
  "scan_timestamp": "2026-03-31T07:58:54.839811",
  "finding_count": 4,
  "findings": [
    {
      "service": "huggingface",
      "file": ".env.local",
      "repository": "sudanva21/Career-Advisor-SIH",
      "url": "https://github.com/sudanva21/Career-Advisor-SIH/blob/36d5272b7d80719b8c19696bbb6500b652ee9b14/.env.local",
      "line_number": 38,
      "line_preview": "HUGGINGFACE_API_KEY=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",
      "key_type": "huggingface_api_key",
      "description": "Huggingface Api Key",
      "severity": "medium",
      "matched_pattern": "HUGG*************************************************AmJS",
      "timestamp": "2026-03-31T07:57:42.867820"
    },
    {
      "service": "huggingface",
      "file": "finlit-gpt/.env.backup",
      "repository": "Nono140503/FinLit-GPT",
      "url": "https://github.com/Nono140503/FinLit-GPT/blob/0f2a1f487fd53b7cd81348e866abda56599cb8d2/finlit-gpt/.env.backup",
      "line_number": 1,
      "line_preview": "HUGGINGFACE_API_KEY=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",
      "key_type": "huggingface_api_key",
      "description": "Huggingface Api Key",
      "severity": "medium",
      "matched_pattern": "HUGG*************************************************TVgD",
      "timestamp": "2026-03-31T07:57:43.630254"
    },
    {
      "service": "huggingface",
      "file": "env.local",
      "repository": "Chumanitikili/FactCast_curse",
      "url": "https://github.com/Chumanitikili/FactCast_curse/blob/09b5aae521245d6a4a4b86cd2ca89225850cde95/env.local",
      "line_number": 32,
      "line_preview": "HUGGINGFACE_API_TOKEN=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",
      "key_type": "huggingface_api_token",
      "description": "Huggingface Api Token",
      "severity": "medium",
      "matched_pattern": "hf_g*****************************xfcH",
      "timestamp": "2026-03-31T07:58:33.483515"
    },
    {
      "service": "huggingface",
      "file": "backend-api/.env.local",
      "repository": "Ricesuu/COS30049-Park-Guide-Training-and-Management",
      "url": "https://github.com/Ricesuu/COS30049-Park-Guide-Training-and-Management/blob/7d461507f2e4b5d101dcc90c02ddc979af3bfad1/backend-api/.env.local",
      "line_number": 19,
      "line_preview": "HUGGINGFACE_API_TOKEN= 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",
      "key_type": "huggingface_api_token",
      "description": "Huggingface Api Token",
      "severity": "medium",
      "matched_pattern": "HUGG****************************************************JfKA",
      "timestamp": "2026-03-31T07:58:34.699952"
    }
  ]
}