{
  "service": "mongo",
  "scan_timestamp": "2026-03-23T07:47:50.941827",
  "finding_count": 1,
  "findings": [
    {
      "service": "mongo",
      "file": ".env.hanzo.example",
      "repository": "hanzoai/chat",
      "url": "https://github.com/hanzoai/chat/blob/7514785db127cb5618a334beda2fc7b77db8f435/.env.hanzo.example",
      "line_number": 15,
      "line_preview": "MONGO_PASSWORD=hanzo123",
      "key_type": "mongo_password",
      "description": "Mongo Password",
      "severity": "high",
      "matched_pattern": "********",
      "timestamp": "2026-03-23T07:47:13.695910"
    }
  ]
}