{
  "service": "serperdev",
  "scan_timestamp": "2026-03-12T06:11:45.357530",
  "finding_count": 1,
  "findings": [
    {
      "service": "serperdev",
      "file": ".env",
      "repository": "davalpez/Local-AI-aplications-with-Haystack",
      "url": "https://github.com/davalpez/Local-AI-aplications-with-Haystack/blob/0daa8316c053423c235aa6c6a23665dc16b3cfb6/.env",
      "line_number": 6,
      "line_preview": "SERPERDEV_API_KEY = #Introduce your API KEY",
      "key_type": "serperdev_api_key",
      "description": "Serperdev Api Key",
      "severity": "medium",
      "matched_pattern": "#Int*************** KEY",
      "timestamp": "2026-03-12T06:10:43.106885"
    }
  ]
}