{
  "service": "canary",
  "scan_timestamp": "2026-03-05T22:08:36.599902",
  "finding_count": 1,
  "findings": [
    {
      "service": "canary",
      "file": "switchboard/switchboard.env.dist",
      "repository": "thinkst/canarytokens",
      "url": "https://github.com/thinkst/canarytokens/blob/dca6147b4002723f842b69fa62682e30a2848f09/switchboard/switchboard.env.dist",
      "line_number": 17,
      "line_preview": "CANARY_WG_PRIVATE_KEY_SEED=vk/GD+frlhve/hDTTSUvqpQ/WsQtioKAri0Rt5mg7dw=",
      "key_type": "canary_wg_private_key_seed",
      "description": "Canary Wg Private Key Seed",
      "severity": "critical",
      "matched_pattern": "vk/G************************************7dw=",
      "timestamp": "2026-03-05T22:00:30.850222"
    }
  ]
}