{
  "service": "icp",
  "scan_timestamp": "2026-03-05T22:08:36.618097",
  "finding_count": 1,
  "findings": [
    {
      "service": "icp",
      "file": ".env",
      "repository": "Sudo-psc/ampar-ai",
      "url": "https://github.com/Sudo-psc/ampar-ai/blob/13c79165d8fc6cca41556e5fd4a79fec25734f2e/.env",
      "line_number": 40,
      "line_preview": "ICP_BRASIL_CERTIFICATE_PATH=\"/path/to/certificate.p12\"",
      "key_type": "icp_brasil_certificate_path",
      "description": "Icp Brasil Certificate Path",
      "severity": "high",
      "matched_pattern": "/pat****************.p12",
      "timestamp": "2026-03-05T22:00:40.949829"
    }
  ]
}