{
  "service": "redsys",
  "scan_timestamp": "2026-03-05T22:08:36.632800",
  "finding_count": 1,
  "findings": [
    {
      "service": "redsys",
      "file": ".env-old",
      "repository": "guiasexcanariasespana/gexexclu",
      "url": "https://github.com/guiasexcanariasespana/gexexclu/blob/506a28466add9b5128d9540230d905e17a96464a/.env-old",
      "line_number": 81,
      "line_preview": "REDSYS_KEY=sq7HjrUOBfKmC576ILgskD5srU870gJ7",
      "key_type": "redsys_key",
      "description": "Redsys Key",
      "severity": "medium",
      "matched_pattern": "sq7H************************0gJ7",
      "timestamp": "2026-03-05T22:07:21.587467"
    }
  ]
}